tourist/__init__.py
tourist/common.py
tourist/app/__init__.py
tourist/app/base/__init__.py
tourist/app/base/schemas.py
tourist/app/routers/__init__.py
tourist/app/routers/auth_mw.py
tourist/app/routers/info/__init__.py
tourist/app/routers/info/routes.py
tourist/app/routers/tour/__init__.py
tourist/app/routers/tour/routes.py
tourist/cli/__init__.py
tourist/client/__init__.py
tourist/client/client.py
tourist/service/__init__.py
tourist/service/driver.py
tourist/service/utils.py
tourist/service/assets/cookie-managers.json
tourist-0.3.1.dist-info/METADATA
tourist-0.3.1.dist-info/WHEEL
tourist-0.3.1.dist-info/entry_points.txt
tourist-0.3.1.dist-info/licenses/LICENSE
tourist-0.3.1.dist-info/RECORD
