Metadata-Version: 2.4
Name: tourist
Version: 0.3.1
Summary: Tourist Framework
Project-URL: Homepage, https://github.com/pogzyb/tourist
Project-URL: Issues, https://github.com/pogzyb/tourist/issues
Author-email: Joe Obarzanek <pogzyb@umich.edu>
License: MIT License
License-File: LICENSE
Classifier: License :: OSI Approved :: MIT License
Classifier: Operating System :: OS Independent
Classifier: Programming Language :: Python :: 3
Requires-Python: >=3.9
Requires-Dist: httpx>=0.23.0
Provides-Extra: app
Requires-Dist: beautifulsoup4>=4.14.3; extra == 'app'
Requires-Dist: fastapi[standard]>=0.112.0; extra == 'app'
Requires-Dist: html-to-markdown>=2.11.1; extra == 'app'
Requires-Dist: patchright==1.56.0; extra == 'app'
Requires-Dist: pydantic==2.8.0; extra == 'app'
Requires-Dist: stamina>=25.2.0; extra == 'app'
Requires-Dist: xvfbwrapper>=0.2.16; extra == 'app'
